{
    "lessons": [
 {"title": "Qisas an-Nabiyyeen 1 | Book Title", "url": "bXdYFJm4eAE", "ie_key": "Youtube", "_type": "url", "id": "bXdYFJm4eAE"}
,{"title": "Qisas an-Nabiyyeen 2 | Name Of The Author", "url": "V9Tc8-BxX3E", "ie_key": "Youtube", "_type": "url", "id": "V9Tc8-BxX3E"}
,{"title": "Qisas an-Nabiyyeen 3 | About The Author, Book and Series", "url": "EsumAzEc60E", "ie_key": "Youtube", "_type": "url", "id": "EsumAzEc60E"}
,{"title": "Qisas an-Nabiyyeen 4 | \u0645\u0646 \u0643\u0633\u0631 \u0627\u0644\u0623\u0635\u0646\u0627\u0645", "url": "SPsvOZhpuwk", "ie_key": "Youtube", "_type": "url", "id": "SPsvOZhpuwk"}
,{"title": "Qisas an-Nabiyyeen 5 | \u0628\u0627\u0626\u0639 \u0627\u0644\u0623\u0635\u0646\u0627\u0645", "url": "GklZpNpHtZo", "ie_key": "Youtube", "_type": "url", "id": "GklZpNpHtZo"}
,{"title": "Qisas an-Nabiyyeen 6 | \u0642\u0628\u0644 \u0623\u064a\u0627\u0645 \u0643\u062b\u064a\u0631\u0629 \u0643\u062b\u064a\u0631\u0629 \u062c\u062f\u0627", "url": "5-Wu8ZSj3zM", "ie_key": "Youtube", "_type": "url", "id": "5-Wu8ZSj3zM"}
,{"title": "Qisas an-Nabiyyeen 7 | \u0643\u0627\u0646 \u0641\u064a \u0642\u0631\u064a\u0629 \u0631\u062c\u0644 \u0645\u0634\u0647\u0648\u0631 \u0645\u0634\u0647\u0648\u0631 \u062c\u062f\u0627", "url": "0ZQ9NmYKvHc", "ie_key": "Youtube", "_type": "url", "id": "0ZQ9NmYKvHc"}
,{"title": "Qisas an-Nabiyyeen 8 | \u0648\u0643\u0627\u0646 \u0627\u0633\u0645 \u0647\u0630\u0627 \u0627\u0644\u0631\u062c\u0644 \u0622\u0632\u0631", "url": "kUeJMqm5vZM", "ie_key": "Youtube", "_type": "url", "id": "kUeJMqm5vZM"}
,{"title": "Qisas an-Nabiyyeen 9 | \u0648\u0643\u0627\u0646 \u0622\u0632\u0631 \u064a\u0628\u064a\u0639 \u0627\u0644\u0623\u0635\u0646\u0627\u0645", "url": "J8yBdi8qvVo", "ie_key": "Youtube", "_type": "url", "id": "J8yBdi8qvVo"}
,{"title": "Qisas an-Nabiyyeen 10 | \u0648\u0643\u0627\u0646 \u0641\u064a \u0647\u0630\u0647 \u0627\u0644\u0642\u0631\u064a\u0629 \u0628\u064a\u062a \u0643\u0628\u064a\u0631 \u062c\u062f\u0627", "url": "1ykdiCe_KiY", "ie_key": "Youtube", "_type": "url", "id": "1ykdiCe_KiY"}
,{"title": "Qisas an-Nabiyyeen 11 | \u0648\u0643\u0627\u0646 \u0641\u064a \u0647\u0630\u0627 \u0627\u0644\u0628\u064a\u062a \u0623\u0635\u0646\u0627\u0645 \u0623\u0635\u0646\u0627\u0645 \u0643\u062b\u064a\u0631\u0629 \u062c\u062f\u0627", "url": "l5tKqrJzQWE", "ie_key": "Youtube", "_type": "url", "id": "l5tKqrJzQWE"}
,{"title": "Qisas an-Nabiyyeen 12 | \u0648\u0643\u0627\u0646 \u0627\u0644\u0646\u0627\u0633 \u064a\u0633\u062c\u062f\u0648\u0646 \u0644\u0647\u0630\u0647 \u0627\u0644\u0623\u0635\u0646\u0627\u0645", "url": "u7lGAWiTtHk", "ie_key": "Youtube", "_type": "url", "id": "u7lGAWiTtHk"}
,{"title": "Qisas an-Nabiyyeen 13 |", "url": "0FcgTl-Ytww", "ie_key": "Youtube", "_type": "url", "id": "0FcgTl-Ytww"}
,{"title": "Qisas an-Nabiyyeen 14 | \u0628\u0627\u0626\u0639 \u0627\u0644\u0623\u0635\u0646\u0627\u0645 (Revision)", "url": "83tFmD_fNPo", "ie_key": "Youtube", "_type": "url", "id": "83tFmD_fNPo"}
,{"title": "Qisas an-Nabiyyeen 15 | \u0628\u0627\u0626\u0639 \u0627\u0644\u0623\u0635\u0646\u0627\u0645 Revision", "url": "6qwyHguWtcs", "ie_key": "Youtube", "_type": "url", "id": "6qwyHguWtcs"}
,{"title": "Qisas an-Nabiyyeen 16 | \u0648\u0644\u062f \u0622\u0632\u0631", "url": "cSqrwsyUmXs", "ie_key": "Youtube", "_type": "url", "id": "cSqrwsyUmXs"}
,{"title": "Qisas an-Nabiyyeen 17 | \u0648\u0644\u062f \u0622\u0632\u0631", "url": "5VXuZb-INIU", "ie_key": "Youtube", "_type": "url", "id": "5VXuZb-INIU"}
,{"title": "Qisas an-Nabiyyeen 18 | \u0648\u0644\u062f \u0622\u0632\u0631", "url": "Ay9DjtwDNHQ", "ie_key": "Youtube", "_type": "url", "id": "Ay9DjtwDNHQ"}
,{"title": "Qisas an-Nabiyyeen 19 | \u0648\u0644\u062f \u0622\u0632\u0631", "url": "3gGq3XPl8dY", "ie_key": "Youtube", "_type": "url", "id": "3gGq3XPl8dY"}
,{"title": "Qisas an-Nabiyyeen 20 | \u0648\u0644\u062f \u0622\u0632\u0631", "url": "7TiWYpRsTD8", "ie_key": "Youtube", "_type": "url", "id": "7TiWYpRsTD8"}
,{"title": "Qisas an-Nabiyyeen 21 | \u0648\u0644\u062f \u0622\u0632\u0631", "url": "Qp--wZxwFY0", "ie_key": "Youtube", "_type": "url", "id": "Qp--wZxwFY0"}
,{"title": "Qisas an-Nabiyyeen 22 | \u0648\u0644\u062f \u0622\u0632\u0631  Revision", "url": "DHdaud1zEtg", "ie_key": "Youtube", "_type": "url", "id": "DHdaud1zEtg"}
,{"title": "Qisas an-Nabiyyeen 23 | Revision", "url": "zua_pRjRhgU", "ie_key": "Youtube", "_type": "url", "id": "zua_pRjRhgU"}
,{"title": "Qisas an-Nabiyyeen 24 | \u0646\u0635\u064a\u062d\u0629 \u0625\u0628\u0631\u0627\u0647\u064a\u0645", "url": "45m2N9mePvc", "ie_key": "Youtube", "_type": "url", "id": "45m2N9mePvc"}
,{"title": "Qisas an-Nabiyyeen 25 | \u0646\u0635\u064a\u062d\u0629 \u0625\u0628\u0631\u0627\u0647\u064a\u0645", "url": "I9ZvnEKVoAU", "ie_key": "Youtube", "_type": "url", "id": "I9ZvnEKVoAU"}
,{"title": "Qisas an-Nabiyyeen 26 | \u0646\u0635\u064a\u062d\u0629 \u0625\u0628\u0631\u0627\u0647\u064a\u0645, Revision 1", "url": "JGsg72C0OSI", "ie_key": "Youtube", "_type": "url", "id": "JGsg72C0OSI"}
,{"title": "Qisas an-Nabiyyeen 27 | \u0646\u0635\u064a\u062d\u0629 \u0625\u0628\u0631\u0627\u0647\u064a\u0645, Revision 2", "url": "6vVJWMe-3s8", "ie_key": "Youtube", "_type": "url", "id": "6vVJWMe-3s8"}
,{"title": "Qisas an-Nabiyyeen 28 | \u0625\u0628\u0631\u0627\u0647\u064a\u0645 \u064a\u0643\u0633\u0631 \u0627\u0644\u0623\u0635\u0646\u0627\u0645", "url": "OngD9-YudDs", "ie_key": "Youtube", "_type": "url", "id": "OngD9-YudDs"}
,{"title": "Qisas an-Nabiyyeen 29 | \u0625\u0628\u0631\u0627\u0647\u064a\u0645 \u064a\u0643\u0633\u0631 \u0627\u0644\u0623\u0635\u0646\u0627\u0645", "url": "p4kcoF7G-ag", "ie_key": "Youtube", "_type": "url", "id": "p4kcoF7G-ag"}
,{"title": "Qisas an-Nabiyyeen 30 | \u0625\u0628\u0631\u0627\u0647\u064a\u0645 \u064a\u0643\u0633\u0631 \u0627\u0644\u0623\u0635\u0646\u0627\u0645", "url": "ONWaoleQZUA", "ie_key": "Youtube", "_type": "url", "id": "ONWaoleQZUA"}
,{"title": "Qisas an-Nabiyyeen 31 | \u0625\u0628\u0631\u0627\u0647\u064a\u0645 \u064a\u0643\u0633\u0631 \u0627\u0644\u0623\u0635\u0646\u0627\u0645", "url": "9uHQHCOq3G0", "ie_key": "Youtube", "_type": "url", "id": "9uHQHCOq3G0"}
,{"title": "Qisas an-Nabiyyeen 32 | \u0625\u0628\u0631\u0627\u0647\u064a\u0645 \u064a\u0643\u0633\u0631 \u0627\u0644\u0623\u0635\u0646\u0627\u0645 Revision", "url": "rNdeN-FIhBo", "ie_key": "Youtube", "_type": "url", "id": "rNdeN-FIhBo"}
,{"title": "Qisas an-Nabiyyeen 33 | \u0625\u0628\u0631\u0627\u0647\u064a\u0645 \u064a\u0643\u0633\u0631 \u0627\u0644\u0623\u0635\u0646\u0627\u0645 Revision Part 2", "url": "25CEH1WybCg", "ie_key": "Youtube", "_type": "url", "id": "25CEH1WybCg"}
,{"title": "Qisas an-Nabiyyeen 34 | \u0625\u0628\u0631\u0627\u0647\u064a\u0645 \u064a\u0643\u0633\u0631 \u0627\u0644\u0623\u0635\u0646\u0627\u0645 Revision Part 3", "url": "6XKmY_JcrdM", "ie_key": "Youtube", "_type": "url", "id": "6XKmY_JcrdM"}
,{"title": "Qisas an-Nabiyyeen 35 | \u0645\u0646 \u0641\u0639\u0644 \u0647\u0630\u0627", "url": "QiR1X41r2Vg", "ie_key": "Youtube", "_type": "url", "id": "QiR1X41r2Vg"}
,{"title": "Qisas an-Nabiyyeen 36 | \u0645\u0646 \u0641\u0639\u0644 \u0647\u0630\u0627", "url": "za5V5s7ak8o", "ie_key": "Youtube", "_type": "url", "id": "za5V5s7ak8o"}
,{"title": "Qisas an-Nabiyyeen 37 | \u0645\u0646 \u0641\u0639\u0644 \u0647\u0630\u0627", "url": "PzBF7JHBIt0", "ie_key": "Youtube", "_type": "url", "id": "PzBF7JHBIt0"}
,{"title": "Qisas an-Nabiyyeen 38 | \u0645\u0646 \u0641\u0639\u0644 \u0647\u0630\u0627", "url": "BuUdtVUqFdA", "ie_key": "Youtube", "_type": "url", "id": "BuUdtVUqFdA"}
,{"title": "Qisas an-Nabiyyeen 39 | \u0645\u0646 \u0641\u0639\u0644 \u0647\u0630\u0627", "url": "S9tZepI8bhs", "ie_key": "Youtube", "_type": "url", "id": "S9tZepI8bhs"}
,{"title": "Qisas an-Nabiyyeen 40 | \u0645\u0646 \u0641\u0639\u0644 \u0647\u0630\u0627 Revision", "url": "qdtErHfjDSo", "ie_key": "Youtube", "_type": "url", "id": "qdtErHfjDSo"}
,{"title": "Qisas an-Nabiyyeen 41 | \u0645\u0646 \u0641\u0639\u0644 \u0647\u0630\u0627 Revision", "url": "-w_POYk1SeI", "ie_key": "Youtube", "_type": "url", "id": "-w_POYk1SeI"}
,{"title": "Qisas an-Nabiyyeen 42 | \u0646\u0627\u0631 \u0628\u0627\u0631\u062f\u0629", "url": "Az2jCI0k2pg", "ie_key": "Youtube", "_type": "url", "id": "Az2jCI0k2pg"}
,{"title": "Qisas an-Nabiyyeen 43 | \u0646\u0627\u0631 \u0628\u0627\u0631\u062f\u0629", "url": "Hs0spPYxR-g", "ie_key": "Youtube", "_type": "url", "id": "Hs0spPYxR-g"}
,{"title": "Qisas an-Nabiyyeen 44 | \u0645\u0646 \u0631\u0628\u064a", "url": "f3jD-wfUtZM", "ie_key": "Youtube", "_type": "url", "id": "f3jD-wfUtZM"}
,{"title": "Qisas an-Nabiyyeen 45 | \u0645\u0646 \u0631\u0628\u064a", "url": "yZmbWTep9mg", "ie_key": "Youtube", "_type": "url", "id": "yZmbWTep9mg"}
]
}